swmming/__init__.py
swmming/inp_sections.py
swmming/xsection_shapes.py
swmming-0.0.1.dist-info/METADATA
swmming-0.0.1.dist-info/WHEEL
swmming-0.0.1.dist-info/RECORD
